pytest_oarepo/__init__.py
pytest_oarepo/files.py
pytest_oarepo/fixtures.py
pytest_oarepo/functions.py
pytest_oarepo/records.py
pytest_oarepo/users.py
pytest_oarepo/communities/__init__.py
pytest_oarepo/communities/fixtures.py
pytest_oarepo/communities/functions.py
pytest_oarepo/communities/records.py
pytest_oarepo/requests/__init__.py
pytest_oarepo/requests/classes.py
pytest_oarepo/requests/fixtures.py
pytest_oarepo/requests/functions.py
pytest_oarepo/ui/__init__.py
pytest_oarepo/ui/classes.py
pytest_oarepo/ui/fixtures.py
pytest_oarepo/vocabularies/__init__.py
pytest_oarepo/vocabularies/config.py
pytest_oarepo/vocabularies/loading.py
pytest_oarepo/vocabularies/data/catalogue.yaml
pytest_oarepo/vocabularies/data/removal_reasons.yaml
pytest_oarepo-2.0.3.dist-info/METADATA
pytest_oarepo-2.0.3.dist-info/WHEEL
pytest_oarepo-2.0.3.dist-info/licenses/LICENSE
pytest_oarepo-2.0.3.dist-info/RECORD
