Metadata-Version: 2.4
Name: pytest-oarepo
Version: 2.0.3
Project-URL: Homepage, https://github.com/oarepo/pytest_oarepo
License-Expression: MIT
License-File: LICENSE
Requires-Python: <3.14,>=3.13
Requires-Dist: oarepo[rdm,tests]<15.0.0,>=14.0.0
Provides-Extra: dev
Requires-Dist: deepmerge; extra == 'dev'
Requires-Dist: oarepo-runtime<3.0.0,>=2.0.0dev13; extra == 'dev'
Requires-Dist: oarepo-workflows<3.0.0,>=2.0.0dev3; extra == 'dev'
Requires-Dist: pytest>=7.1.2; extra == 'dev'
Provides-Extra: oarepo14
Requires-Dist: oarepo[rdm,tests]<15.0.0,>=14.0.0; extra == 'oarepo14'
Provides-Extra: tests
Requires-Dist: pytest>=7.1.2; extra == 'tests'
